umierrorcorrect/__init__.py
umierrorcorrect/call_variants.py
umierrorcorrect/downsampling_plots.py
umierrorcorrect/filter_bam.py
umierrorcorrect/filter_cons.py
umierrorcorrect/filter_cons2.py
umierrorcorrect/filter_vcf.py
umierrorcorrect/fit_background_model.py
umierrorcorrect/get_consensus_statistics.py
umierrorcorrect/get_consensus_statistics2.py
umierrorcorrect/get_umi_cluster_info.py
umierrorcorrect/preprocess.py
umierrorcorrect/run_mapping.py
umierrorcorrect/run_umierrorcorrect.py
umierrorcorrect/test_cons_info_indel.py
umierrorcorrect/umi_error_correct.py
umierrorcorrect/version.py
umierrorcorrect/src/__init__.py
umierrorcorrect/src/check_args.py
umierrorcorrect/src/get_cons_info.py
umierrorcorrect/src/get_consensus3.py
umierrorcorrect/src/get_regions_from_bed.py
umierrorcorrect/src/group.py
umierrorcorrect/src/handle_sequences.py
umierrorcorrect/src/umi_cluster.py
umierrorcorrect-0.26.data/scripts/call_variants.py
umierrorcorrect-0.26.data/scripts/downsampling_plots.py
umierrorcorrect-0.26.data/scripts/filter_bam.py
umierrorcorrect-0.26.data/scripts/filter_cons.py
umierrorcorrect-0.26.data/scripts/fit_background_model.py
umierrorcorrect-0.26.data/scripts/get_consensus_statistics.py
umierrorcorrect-0.26.data/scripts/preprocess.py
umierrorcorrect-0.26.data/scripts/run_mapping.py
umierrorcorrect-0.26.data/scripts/run_umierrorcorrect.py
umierrorcorrect-0.26.data/scripts/umi_error_correct.py
umierrorcorrect-0.26.dist-info/LICENSE.txt
umierrorcorrect-0.26.dist-info/METADATA
umierrorcorrect-0.26.dist-info/WHEEL
umierrorcorrect-0.26.dist-info/top_level.txt
umierrorcorrect-0.26.dist-info/RECORD
